xpython_launcher.py
xeus_python-0.17.6.dist-info/RECORD
xeus_python-0.17.6.dist-info/LICENSE
xeus_python-0.17.6.dist-info/WHEEL
xeus_python-0.17.6.dist-info/top_level.txt
xeus_python-0.17.6.dist-info/METADATA
xpython/__init__.py
xpython/xpython_extension.cpython-311-darwin.so
xeus_python-0.17.6.data/data/share/jupyter/kernels/xpython/kernel.json
xeus_python-0.17.6.data/data/share/jupyter/kernels/xpython/logo-64x64.png
xeus_python-0.17.6.data/data/share/jupyter/kernels/xpython/logo-32x32.png
xeus_python-0.17.6.data/data/share/jupyter/kernels/xpython-raw/kernel.json
xeus_python-0.17.6.data/data/share/jupyter/kernels/xpython-raw/logo-64x64.png
xeus_python-0.17.6.data/data/share/jupyter/kernels/xpython-raw/logo-32x32.png
